llmdump/__init__.py
llmdump/__main__.py
llmdump/__version__.py
llmdump/config.py
llmdump/py.typed
llmdump/axle/__init__.py
llmdump/cli/__init__.py
llmdump/cli/main.py
llmdump/hub/__init__.py
llmdump/hub/connection.py
llmdump/hub/loader.py
llmdump/hub/query.py
llmdump/hub/supply_chain.py
llmdump/oracle/__init__.py
llmdump/oracle/commit_analyzer.py
llmdump/oracle/integrated_oracle.py
llmdump/oracle/predictor.py
llmdump/spokes/__init__.py
llmdump/spokes/base.py
llmdump/spokes/cve.py
llmdump/spokes/cwe.py
llmdump/spokes/epss.py
llmdump/spokes/exploit_db.py
llmdump/spokes/github.py
llmdump/spokes/github_advisory.py
llmdump/spokes/kev.py
llmdump/spokes/package.py
llmdump/utils/__init__.py
llmdump/wheel/__init__.py
llmdump-0.1.0.dist-info/licenses/LICENSE
scripts/check_status.py
scripts/collect_data.py
scripts/collect_image_dataset.py
scripts/load_to_neo4j.py
scripts/red_team_attacks.py
scripts/archive/check_neo4j_data.py
scripts/archive/analysis/analyze_cve_commits.py
scripts/archive/analysis/analyze_cve_github_links.py
scripts/archive/analysis/attack_pattern_analysis.py
scripts/archive/analysis/check_attack_types.py
scripts/archive/analysis/check_data_coverage.py
scripts/archive/analysis/contributor_influence_analysis.py
scripts/archive/analysis/find_vulnerability_origin.py
scripts/archive/analysis/llm_commit_analysis.py
scripts/archive/collection/collect_all_cves.py
scripts/archive/collection/collect_bulk_cve.py
scripts/archive/collection/collect_epss_bulk.py
scripts/archive/collection/collect_exploits_bulk.py
scripts/archive/collection/collect_github_advisory_bulk.py
scripts/archive/collection/collect_github_commits_bulk.py
scripts/archive/collection/collect_github_commits_by_cve.py
scripts/archive/collection/collect_github_commits_smart.py
scripts/archive/collection/collect_kev.py
scripts/archive/collection/collect_paper_dataset.py
scripts/archive/deployment/publish_to_pypi.py
scripts/archive/loading/analyze_all_commit_sources.py
scripts/archive/loading/analyze_commits.py
llmdump-0.1.0.dist-info/METADATA
llmdump-0.1.0.dist-info/WHEEL
llmdump-0.1.0.dist-info/entry_points.txt
llmdump-0.1.0.dist-info/top_level.txt
llmdump-0.1.0.dist-info/RECORD
