Metadata-Version: 2.4
Name: llmdump
Version: 0.1.0
Summary: Security analysis framework for LLM-generated content in software development
Author-email: Susie Choi <sschoidev@gmail.com>
Maintainer-email: Susie Choi <sschoidev@gmail.com>
License: MIT
Project-URL: Homepage, https://github.com/susie-Choi/llmdump
Project-URL: Repository, https://github.com/susie-Choi/llmdump
Project-URL: Documentation, https://github.com/susie-Choi/llmdump#readme
Project-URL: Bug Tracker, https://github.com/susie-Choi/llmdump/issues
Project-URL: Changelog, https://github.com/susie-Choi/llmdump/releases
Keywords: security,vulnerability,zero-day,prediction,ai,machine-learning,cybersecurity,threat-assessment
Classifier: Development Status :: 3 - Alpha
Classifier: Intended Audience :: Developers
Classifier: Intended Audience :: Information Technology
Classifier: Intended Audience :: Science/Research
Classifier: License :: OSI Approved :: MIT License
Classifier: Operating System :: OS Independent
Classifier: Programming Language :: Python :: 3
Classifier: Programming Language :: Python :: 3.10
Classifier: Programming Language :: Python :: 3.11
Classifier: Programming Language :: Python :: 3.12
Classifier: Topic :: Security
Classifier: Topic :: Scientific/Engineering :: Artificial Intelligence
Classifier: Topic :: Software Development :: Libraries :: Python Modules
Requires-Python: >=3.10
License-File: LICENSE
Requires-Dist: pyyaml>=6.0
Requires-Dist: requests>=2.31.0
Requires-Dist: tqdm>=4.66.0
Requires-Dist: matplotlib>=3.7.0
Requires-Dist: seaborn>=0.12.0
Requires-Dist: scipy>=1.10.0
Requires-Dist: statsmodels>=0.14.0
Provides-Extra: dev
Requires-Dist: pytest>=7.0; extra == "dev"
Requires-Dist: pytest-cov>=4.0; extra == "dev"
Requires-Dist: black>=23.0; extra == "dev"
Requires-Dist: flake8>=6.0; extra == "dev"
Requires-Dist: mypy>=1.0; extra == "dev"
Provides-Extra: neo4j
Requires-Dist: neo4j>=5.0; extra == "neo4j"
Requires-Dist: py2neo>=2021.2; extra == "neo4j"
Provides-Extra: dashboard
Requires-Dist: streamlit>=1.28.0; extra == "dashboard"
Requires-Dist: plotly>=5.17.0; extra == "dashboard"
Requires-Dist: pandas>=2.0.0; extra == "dashboard"
Dynamic: license-file
